torchagent/__init__.py
torchagent/agents/__init__.py
torchagent/agents/dqn.py
torchagent/memory.py
torchagent/policy.py
torchagent-0.2.4.dist-info/WHEEL
torchagent-0.2.4.dist-info/METADATA
torchagent-0.2.4.dist-info/RECORD
