Metadata-Version: 2.1
Name: torchagent
Version: 0.2.4
Summary: Deep-Q learning with pytorch
Home-page: https://github.com/wmeints/torchagent
License: Apache-2.0
Author: Willem Meints
Author-email: willem.meints@gmail.com
Requires-Python: >=3.8
Classifier: Development Status :: 1 - Planning
Classifier: Intended Audience :: Developers
Classifier: License :: OSI Approved :: Apache Software License
Classifier: Programming Language :: Python
Classifier: Programming Language :: Python :: 3
Classifier: Programming Language :: Python :: 3.8
Classifier: Programming Language :: Python :: 3.9
Classifier: Programming Language :: Python :: Implementation :: CPython
Classifier: Programming Language :: Python :: Implementation :: PyPy
Requires-Dist: torch (>=1.8.1,<2.0.0)
Project-URL: Repository, https://github.com/wmeints/torchagent
